setup.cfg
setup.py
django_leancloud_sms.egg-info/PKG-INFO
django_leancloud_sms.egg-info/SOURCES.txt
django_leancloud_sms.egg-info/dependency_links.txt
django_leancloud_sms.egg-info/not-zip-safe
django_leancloud_sms.egg-info/requires.txt
django_leancloud_sms.egg-info/top_level.txt
leancloud/__init__.py
leancloud/exceptions.py
leancloud/sms.py
testapp/__init__.py
testapp/manage.py
testapp/settings.py
testapp/urls.py
testapp/wsgi.py
testapp/sms/__init__.py
testapp/sms/models.py
testapp/sms/tests.py
testapp/sms/views.py