Metadata-Version: 1.1
Name: django-leancloud-sms
Version: 0.3
Summary: A simple Django app use leancloud sms api
Home-page: https://github.com/edison7500/django-leancloud-sms
Author: jiaxin
Author-email: edison7500@gmail.com
License: BSD License
Download-URL: https://github.com/edison7500/django-leancloud-sms/archive/v0.2-alpha.tar.gz
Platform: UNKNOWN
Classifier: Environment :: Web Environment
Classifier: Framework :: Django
Classifier: Framework :: Django :: 1.8
Classifier: License :: OSI Approved :: BSD License
Classifier: Operating System :: OS Independent
Classifier: Programming Language :: Python
Classifier: Programming Language :: Python :: 2.7
Classifier: Topic :: Internet :: WWW/HTTP
Classifier: Topic :: Internet :: WWW/HTTP :: Dynamic Content
